odoo/addons/delivery_carrier_warehouse/README.rst
odoo/addons/delivery_carrier_warehouse/__init__.py
odoo/addons/delivery_carrier_warehouse/__manifest__.py
odoo/addons/delivery_carrier_warehouse/i18n/delivery_carrier_warehouse.pot
odoo/addons/delivery_carrier_warehouse/i18n/es_AR.po
odoo/addons/delivery_carrier_warehouse/i18n/it.po
odoo/addons/delivery_carrier_warehouse/models/__init__.py
odoo/addons/delivery_carrier_warehouse/models/sale_order.py
odoo/addons/delivery_carrier_warehouse/models/stock_warehouse.py
odoo/addons/delivery_carrier_warehouse/readme/CONTRIBUTORS.md
odoo/addons/delivery_carrier_warehouse/readme/CREDITS.md
odoo/addons/delivery_carrier_warehouse/readme/DESCRIPTION.md
odoo/addons/delivery_carrier_warehouse/static/description/icon.png
odoo/addons/delivery_carrier_warehouse/static/description/index.html
odoo/addons/delivery_carrier_warehouse/tests/__init__.py
odoo/addons/delivery_carrier_warehouse/tests/test_delivery_carrier_warehouse.py
odoo/addons/delivery_carrier_warehouse/views/stock_warehouse.xml
odoo_addon_delivery_carrier_warehouse-18.0.1.0.1.1.dist-info/METADATA
odoo_addon_delivery_carrier_warehouse-18.0.1.0.1.1.dist-info/WHEEL
odoo_addon_delivery_carrier_warehouse-18.0.1.0.1.1.dist-info/top_level.txt
odoo_addon_delivery_carrier_warehouse-18.0.1.0.1.1.dist-info/RECORD
